aldakit/__init__.py
aldakit/__main__.py
aldakit/_libremidi.cpython-311-x86_64-linux-gnu.so
aldakit/_tsf.cpython-311-x86_64-linux-gnu.so
aldakit/api.py
aldakit/ast_nodes.py
aldakit/cli.py
aldakit/config.py
aldakit/constants.py
aldakit/errors.py
aldakit/parser.py
aldakit/repl.py
aldakit/scanner.py
aldakit/score.py
aldakit/tokens.py
aldakit/compose/__init__.py
aldakit/compose/attributes.py
aldakit/compose/base.py
aldakit/compose/chords.py
aldakit/compose/core.py
aldakit/compose/generate.py
aldakit/compose/part.py
aldakit/compose/scales.py
aldakit/compose/transform.py
aldakit/ext/__init__.py
aldakit/ext/prompt_toolkit/__init__.py
aldakit/ext/prompt_toolkit/auto_suggest.py
aldakit/ext/prompt_toolkit/buffer.py
aldakit/ext/prompt_toolkit/cache.py
aldakit/ext/prompt_toolkit/cursor_shapes.py
aldakit/ext/prompt_toolkit/data_structures.py
aldakit/ext/prompt_toolkit/document.py
aldakit/ext/prompt_toolkit/enums.py
aldakit/ext/prompt_toolkit/history.py
aldakit/ext/prompt_toolkit/keys.py
aldakit/ext/prompt_toolkit/log.py
aldakit/ext/prompt_toolkit/mouse_events.py
aldakit/ext/prompt_toolkit/patch_stdout.py
aldakit/ext/prompt_toolkit/py.typed
aldakit/ext/prompt_toolkit/renderer.py
aldakit/ext/prompt_toolkit/search.py
aldakit/ext/prompt_toolkit/selection.py
aldakit/ext/prompt_toolkit/token.py
aldakit/ext/prompt_toolkit/utils.py
aldakit/ext/prompt_toolkit/validation.py
aldakit/ext/prompt_toolkit/win32_types.py
aldakit/ext/prompt_toolkit/application/__init__.py
aldakit/ext/prompt_toolkit/application/application.py
aldakit/ext/prompt_toolkit/application/current.py
aldakit/ext/prompt_toolkit/application/dummy.py
aldakit/ext/prompt_toolkit/application/run_in_terminal.py
aldakit/ext/prompt_toolkit/clipboard/__init__.py
aldakit/ext/prompt_toolkit/clipboard/base.py
aldakit/ext/prompt_toolkit/clipboard/in_memory.py
aldakit/ext/prompt_toolkit/clipboard/pyperclip.py
aldakit/ext/prompt_toolkit/completion/__init__.py
aldakit-0.1.10.dist-info/METADATA
aldakit-0.1.10.dist-info/WHEEL
aldakit-0.1.10.dist-info/entry_points.txt
aldakit-0.1.10.dist-info/RECORD
aldakit-0.1.10.dist-info/licenses/LICENSE
