Metadata-Version: 2.4
Name: aldakit
Version: 0.1.10
Summary: Python parser and MIDI generator for the Alda music programming language
Keywords: alda,midi,music,parser,composition,audio
Author-Email: Shakeeb Alireza <shakfu@users.noreply.github.com>
License-Expression: MIT
Classifier: Development Status :: 3 - Alpha
Classifier: Intended Audience :: Developers
Classifier: Intended Audience :: End Users/Desktop
Classifier: Operating System :: MacOS
Classifier: Operating System :: POSIX :: Linux
Classifier: Operating System :: Microsoft :: Windows
Classifier: Programming Language :: Python :: 3
Classifier: Programming Language :: Python :: 3.10
Classifier: Programming Language :: Python :: 3.11
Classifier: Programming Language :: Python :: 3.12
Classifier: Programming Language :: Python :: 3.13
Classifier: Programming Language :: Python :: 3.14
Classifier: Topic :: Multimedia :: Sound/Audio :: MIDI
Classifier: Topic :: Software Development :: Libraries :: Python Modules
Project-URL: Homepage, https://github.com/shakfu/aldakit
Project-URL: Repository, https://github.com/shakfu/aldakit
Project-URL: Documentation, https://github.com/shakfu/aldakit#readme
Project-URL: Changelog, https://github.com/shakfu/aldakit/blob/main/CHANGELOG.md
Requires-Python: >=3.10
